Metadata-Version: 2.1
Name: setupyntx
Version: 0.0.1
Summary: by setupyntx
Author-email: <setupyntx@gmail.com>
License: Eclipse Public License 2.0
Keywords: setupyntx,pystyle
